config/__init__.py
config/__main__.py
config/_config.py
config/auth.py
config/cf.py
config/cfenv.py
config/cli.py
config/cloudfoundry.py
config/core.py
config/exceptions.py
config/http.py
config/logger.py
config/spring.py
config/ext/__init__.py
config/ext/aiohttp.py
config/ext/fastapi.py
config/ext/flask.py
tests/__init__.py
tests/conftest.py
tests/unit/__init__.py
tests/unit/test_cf.py
tests/unit/test_cfenv.py
tests/unit/test_cli.py
tests/unit/test_config.py
tests/unit/test_http.py
tests/unit/test_oauth2.py
tests/unit/test_spring.py
tests/unit/ext/__init__.py
tests/unit/ext/test_aiohttp.py
tests/unit/ext/test_flask.py
config_client-1.4.0.dist-info/LICENSE
config_client-1.4.0.dist-info/METADATA
config_client-1.4.0.dist-info/WHEEL
config_client-1.4.0.dist-info/entry_points.txt
config_client-1.4.0.dist-info/top_level.txt
config_client-1.4.0.dist-info/RECORD
