Metadata-Version: 2.1
Name: config-client
Version: 1.4.0
Summary: config client for Spring Cloud Config Server and Cloud Foundry
Home-page: https://github.com/amenezes/config-client
Author: Alexandre Menezes
Author-email: alexandre.fmenezes@gmail.com
License: Apache-2.0
Project-URL: Documentation, https://config-client.amenezes.net
Project-URL: Code, https://github.com/amenezes/config-client
Project-URL: Issue tracker, https://github.com/amenezes/config-client/issues
Project-URL: Changes, https://github.com/amenezes/config-client/releases
Keywords: ['spring','cloudfoundry','springcloud']
Classifier: Development Status :: 5 - Production/Stable
Classifier: Framework :: AsyncIO
Classifier: Framework :: Flask
Classifier: Intended Audience :: Developers
Classifier: License :: OSI Approved :: Apache Software License
Classifier: Operating System :: OS Independent
Classifier: Programming Language :: Python :: 3 :: Only
Classifier: Programming Language :: Python :: 3.7
Classifier: Programming Language :: Python :: 3.8
Classifier: Programming Language :: Python :: 3.9
Classifier: Programming Language :: Python :: 3.10
Classifier: Programming Language :: Python :: 3.11
Classifier: Programming Language :: Python :: 3.12
Classifier: Programming Language :: Python :: Implementation :: CPython
Classifier: Programming Language :: Python :: Implementation :: PyPy
Classifier: Topic :: Software Development :: Libraries
Classifier: Topic :: Software Development :: Libraries :: Java Libraries
Requires-Python: >=3.7
License-File: LICENSE
Requires-Dist: attrs>=21.3.0
Requires-Dist: glom>=19.2.0
Requires-Dist: requests>=2.22.0
Provides-Extra: cli
Requires-Dist: click>=8.1.3; extra == "cli"
Requires-Dist: rich>=12.6.0; extra == "cli"
Requires-Dist: trogon>=0.5.0; extra == "cli"
Provides-Extra: docs
Requires-Dist: mkdocs-material; extra == "docs"
Provides-Extra: all
Requires-Dist: click>=8.1.3; extra == "all"
Requires-Dist: mkdocs-material; extra == "all"
Requires-Dist: rich>=12.6.0; extra == "all"
Requires-Dist: trogon>=0.5.0; extra == "all"
